{
  "nameDepartment": "D00",
  "description": "หลักสูตรภาคทดสอบ พ.ศ. 2560",
  "startYear": 2560,
  "category": [
    {
      "categoryName": "test",
      "atLeastCredit": 4,
      "expression": null,
      "subCategory": [
        {
          "categoryName": "ทดสอบ2",
          "atLeastCredit": "2",
          "expression": [],
          "subCategory": [],
          "showSubject": false
        },
        {
          "categoryName": "ทดสอบ3",
          "atLeastCredit": "2",
          "expression": [],
          "subCategory": [],
          "showSubject": false
        }
      ],
      "showSubject": false
    }
  ],
  "test": "1",
  "numberOfYear": 1,
  "semesterYears": [
    {
      "firstSemester": [
        {
          "subjectCode": "01418112",
          "subjectCodeType": "regex",
          "subjectName": "fundamental concept",
          "subjectCategory": "ทดสอบ2",
          "isGroupType": false
        },
        {
          "subjectCode": "general_educated_sci",
          "subjectCodeType": "group",
          "subjectName": "(วิชาทั่วไป ในคณะวิทยาศาสตร์)",
          "subjectCategory": "ทดสอบ3",
          "isGroupType": true
        }
      ],
      "secondSemester": []
    },
    { "firstSemester": [], "secondSemester": [] },
    { "firstSemester": [], "secondSemester": [] },
    { "firstSemester": [], "secondSemester": [] }
  ]
}
